odoo/addons/l10n_br_account/README.rst
odoo/addons/l10n_br_account/__init__.py
odoo/addons/l10n_br_account/__manifest__.py
odoo/addons/l10n_br_account/hooks.py
odoo/addons/l10n_br_account/data/account_tax_group.xml
odoo/addons/l10n_br_account/data/account_tax_template.xml
odoo/addons/l10n_br_account/demo/res_users_demo.xml
odoo/addons/l10n_br_account/i18n/l10n_br_account.pot
odoo/addons/l10n_br_account/i18n/pt_BR.po
odoo/addons/l10n_br_account/images/l10n_br-hover.png
odoo/addons/l10n_br_account/images/l10n_br.png
odoo/addons/l10n_br_account/models/__init__.py
odoo/addons/l10n_br_account/models/account_chart_template.py
odoo/addons/l10n_br_account/models/account_incoterms.py
odoo/addons/l10n_br_account/models/account_journal.py
odoo/addons/l10n_br_account/models/account_move.py
odoo/addons/l10n_br_account/models/account_move_line.py
odoo/addons/l10n_br_account/models/account_tax.py
odoo/addons/l10n_br_account/models/account_tax_group.py
odoo/addons/l10n_br_account/models/account_tax_template.py
odoo/addons/l10n_br_account/models/constants.py
odoo/addons/l10n_br_account/models/document.py
odoo/addons/l10n_br_account/models/document_line.py
odoo/addons/l10n_br_account/models/fiscal_decorator_mixin.py
odoo/addons/l10n_br_account/models/fiscal_operation.py
odoo/addons/l10n_br_account/models/fiscal_operation_line.py
odoo/addons/l10n_br_account/models/fiscal_tax.py
odoo/addons/l10n_br_account/models/fiscal_tax_group.py
odoo/addons/l10n_br_account/models/ir_model_data.py
odoo/addons/l10n_br_account/readme/CONFIGURE.md
odoo/addons/l10n_br_account/readme/CONTRIBUTORS.md
odoo/addons/l10n_br_account/readme/DESCRIPTION.md
odoo/addons/l10n_br_account/readme/HISTORY.md
odoo/addons/l10n_br_account/readme/INSTALL.md
odoo/addons/l10n_br_account/readme/ROADMAP.md
odoo/addons/l10n_br_account/readme/USAGE.md
odoo/addons/l10n_br_account/report/__init__.py
odoo/addons/l10n_br_account/report/account_invoice_report.py
odoo/addons/l10n_br_account/report/account_invoice_report_view.xml
odoo_addon_l10n_br_account-16.0.14.0.0.dist-info/METADATA
odoo_addon_l10n_br_account-16.0.14.0.0.dist-info/WHEEL
odoo_addon_l10n_br_account-16.0.14.0.0.dist-info/top_level.txt
odoo_addon_l10n_br_account-16.0.14.0.0.dist-info/RECORD
